wtpsplit/__init__.py
wtpsplit/configs.py
wtpsplit/extract.py
wtpsplit/extract_batched.py
wtpsplit/models.py
wtpsplit/data/__init__.py
wtpsplit/data/language_info.csv
wtpsplit/data/punctuation.json
wtpsplit/data/punctuation.txt
wtpsplit/data/punctuation_xlmr.txt
wtpsplit/data/punctuation_xlmr_unk.txt
wtpsplit/data_acquisition/__init__.py
wtpsplit/data_acquisition/extract_all_data.py
wtpsplit/data_acquisition/extract_eval_data.py
wtpsplit/data_acquisition/extract_sentences.py
wtpsplit/data_acquisition/extract_shared_task_data.py
wtpsplit/evaluation/__init__.py
wtpsplit/evaluation/adapt.py
wtpsplit/evaluation/evaluate_sepp_nlg_subtask1.py
wtpsplit/evaluation/extrinsic.py
wtpsplit/evaluation/intrinsic_baselines.py
wtpsplit/evaluation/intrinsic_baselines_multilingual.py
wtpsplit/evaluation/intrinsic_pairwise.py
wtpsplit/evaluation/intrinsic_ted.py
wtpsplit/evaluation/legal_baselines.py
wtpsplit/evaluation/llm_sentence.py
wtpsplit/evaluation/punct_annotation.py
wtpsplit/evaluation/punct_annotation_wtp.py
wtpsplit/train/__init__.py
wtpsplit/train/adaptertrainer.py
wtpsplit/train/evaluate.py
wtpsplit/train/train.py
wtpsplit/train/train_SM.py
wtpsplit/train/train_lora.py
wtpsplit/train/trainer.py
wtpsplit/train/utils.py
wtpsplit/utils/__init__.py
wtpsplit/utils/clean_tweets.py
wtpsplit/utils/create_dummy_data.py
wtpsplit/utils/download_spacy.py
wtpsplit/utils/remove_unks.py
wtpsplit-2.1.7.dist-info/licenses/LICENSE
wtpsplit-2.1.7.dist-info/METADATA
wtpsplit-2.1.7.dist-info/WHEEL
wtpsplit-2.1.7.dist-info/top_level.txt
wtpsplit-2.1.7.dist-info/RECORD
