Metadata-Version: 2.4
Name: wtpsplit
Version: 2.1.7
Summary: Universal Robust, Efficient and Adaptable Sentence Segmentation
Home-page: https://github.com/segment-any-text/wtpsplit
Author: Markus Frohmann, Igor Sterner, Benjamin Minixhofer
Author-email: markus.frohmann@gmail.com
License: MIT
License-File: LICENSE
Requires-Dist: transformers>=4.22.2
Requires-Dist: huggingface-hub
Requires-Dist: numpy>=1.0
Requires-Dist: scikit-learn>=1
Requires-Dist: tqdm
Requires-Dist: skops
Requires-Dist: pandas>=1
Requires-Dist: cached_property
Requires-Dist: mosestokenizer
Requires-Dist: adapters>=1.0.1
Provides-Extra: onnx-gpu
Requires-Dist: onnxruntime-gpu>=1.13.1; extra == "onnx-gpu"
Provides-Extra: onnx-cpu
Requires-Dist: onnxruntime>=1.13.1; extra == "onnx-cpu"
Dynamic: author
Dynamic: author-email
Dynamic: home-page
Dynamic: license
Dynamic: license-file
Dynamic: provides-extra
Dynamic: requires-dist
Dynamic: summary
